rest_toolkit/__init__.py
rest_toolkit/abc.py
rest_toolkit/compat.py
rest_toolkit/error.py
rest_toolkit/state.py
rest_toolkit/utils.py
rest_toolkit/views.py
rest_toolkit/ext/__init__.py
rest_toolkit/ext/colander.py
rest_toolkit/ext/jsonschema.py
rest_toolkit/ext/sql.py
rest_toolkit-0.17.dist-info/LICENSE
rest_toolkit-0.17.dist-info/METADATA
rest_toolkit-0.17.dist-info/WHEEL
rest_toolkit-0.17.dist-info/pbr.json
rest_toolkit-0.17.dist-info/top_level.txt
rest_toolkit-0.17.dist-info/zip-safe
rest_toolkit-0.17.dist-info/RECORD
