Metadata-Version: 2.1
Name: rest-toolkit
Version: 0.17
Summary: REST toolkit
Home-page: https://github.com/wichert/rest_toolkit
Author: Wichert Akkerman
Author-email: wichert@wiggy.net
License: BSD
Keywords: REST Pyramid
Platform: UNKNOWN
Classifier: Development Status :: 3 - Alpha
Classifier: Environment :: Web Environment
Classifier: Framework :: Pyramid
Classifier: Intended Audience :: Developers
Classifier: License :: DFSG approved
Classifier: License :: OSI Approved :: BSD License
Classifier: Operating System :: OS Independent
Classifier: Programming Language :: Python :: 2
Classifier: Programming Language :: Python :: 2.7
Classifier: Programming Language :: Python :: 3
Classifier: Programming Language :: Python :: 3.4
Classifier: Programming Language :: Python :: 3.5
Classifier: Programming Language :: Python :: 3.6
Classifier: Topic :: Internet :: WWW/HTTP :: WSGI
Classifier: Topic :: Software Development :: Libraries :: Python Modules
Requires-Dist: pyramid (>=1.6a2)
Provides-Extra: tests
Requires-Dist: pytest; extra == 'tests'
Requires-Dist: WebTest; extra == 'tests'
Requires-Dist: colander; extra == 'tests'
Requires-Dist: jsonschema; extra == 'tests'
Requires-Dist: pyramid-sqlalchemy (>=1.2); extra == 'tests'
Requires-Dist: pyramid-tm; extra == 'tests'
